<?xml version="1.0" encoding="UTF-8"?>
<!--

     Copyright (c) 2009-2011 Misys Open Source Solutions (MOSS) and others

     Licensed under the Apache License, Version 2.0 (the "License");
     you may not use this file except in compliance with the License.
     You may obtain a copy of the License at

        http://www.apache.org/licenses/LICENSE-2.0

     Unless required by applicable law or agreed to in writing, software
     distributed under the License is distributed on an "AS IS" BASIS,
     WITHOUT WARRANTIES OR CONDITIONS OF ANY KIND, either express or
     implied. See the License for the specific language governing
     permissions and limitations under the License.

     Contributors:
       Misys Open Source Solutions - initial API and implementation


-->
<!--Note: This file is the starting point of All the Actor configuration;
	all other config files should be linked from here. -->

<!--Each configuration file has a root Configuration tag-->
<Configuration>

	<!--Defines the configuration of Audit Repository Server for Audit Client-->
	<ConnectionFile file="AuditRepositoryConnections.xml" />
	<!--Defines the configuration of XDS Registry-->
	<ConnectionFile file="XdsRegistryConnections.xml" />
	<!--Defines the configuration of XDS Repository-->
	<ConnectionFile file="XdsRepositoryConnections.xml" />
	<!--Defines the configuration of XCA Responding Gateway-->
	<ConnectionFile file="XcaRespondingGatewayConnections.xml" />
	<!--Defines the configuration of XCA Initiating Gateway-->
	<ConnectionFile file="XcaInitiatingGatewayConnections.xml" />

	<!--The XDS Registry actor configuration-->
	<Actor name="xdsreg" type="XdsRegistry">
		<Description>XDS Registry</Description>
		<Connection type="PixServer" name="pix-registry"/>
		<!-- Uncomment to enable DSUB publish transaction to DSUB broker -->
	    <!-- <Connection type="DsubBroker" name="local-broker"/>    -->
        <Includefile name="XdsCodes.xml" />		
        <Identifier type="globalDomain" name="GLOBAL">
			<UniversalId>1.3.6.1.4.1.21367.13.20.3000</UniversalId>
			<UniversalIdType>ISO</UniversalIdType>
        </Identifier>
	</Actor>
 
	<!--The XDS Repository actor configuration-->
	<Actor name="xdsrep" type="XdsRepository">
		<Description>XDS Repository</Description>
		<Connection type="Registry" name="xds-registry-client"/>
	</Actor>

	<!--The XCA Responding Gateway actor configuration-->
	<!-- Actor name="xcarg" type="XcaRG">
		<Description>XCA Responding Gateway</Description>
		<Connection type="Registry" name="misys-registry"/>
		<Connection type="Repository" name="misys-repository"/>
	</Actor-->
	
	<!--The XCA Initiating Gateway actor configuration-->
	<!-- Actor name="xcaig" type="XcaIG">
		<Description>XCA Initiating Gateway</Description>
		<Connection type="Registry" name="local-registry"/>
		<Connection type="Repository" name="local-repository"/>
		<TransactionsSet type="RespondingGateway">
			<Transactions id="urn:oid:1.3.6.1.4.1.21367.13.3000" query="alert-rg" retrieve="alert-rg"/>
			<Transactions id="urn:oid:1.3.6.1.4.1.21367.13.3005" query="axolotl-rg-query" retrieve="axolotl-rg-retrieve"/>
			<Transactions id="urn:oid:1.3.6.1.4.1.21367.13.3010" query="emc-rg-query" retrieve="emc-rg-retrieve"/>
			<Transactions id="urn:oid:1.3.6.1.4.1.21367.13.3017" query="forcare-secure-rg-query" retrieve="forcare-secure-rg-retrieve"/>
			<Transactions id="urn:oid:1.3.6.1.4.1.21367.13.3025" query="ibm-rg-query" retrieve="ibm-rg-retrieve"/>
			<Transactions id="urn:oid:1.3.6.1.4.1.21367.13.3030" query="siemens-rg" retrieve="siemens-rg"/>
			<Transactions id="urn:oid:1.3.6.1.4.1.21367.13.3035" query="lawson-rg-query" retrieve="lawson-rg-retrieve"/>
			<Transactions id="urn:oid:1.3.6.1.4.1.21367.13.3040" query="medecision-rg-query" retrieve="medecision-rg-retrieve"/>
			<Transactions id="urn:oid:1.3.6.1.4.1.21367.13.3045" query="medicity-rg" retrieve="medicity-rg"/>
			<Transactions id="urn:oid:1.3.6.1.4.1.21367.13.3050" query="local-rg" retrieve="local-rg"/>
			<Transactions id="urn:oid:1.3.6.1.4.1.21367.13.3065" query="tiani-secure-rg" retrieve="tiani-secure-rg"/>
			<Transactions id="urn:oid:1.3.6.1.4.1.21367.13.3070" query="vangent-rg" retrieve="vangent-rg"/>
		</TransactionsSet>
	</Actor-->
	
    <!--=========================================================-->     
 	<!-- Audit Record Repository Configuration                   -->
    <!--=========================================================-->     
    <Actor name="auditlog" type="SecureNode">
		<Description>Audit Record Repository</Description>
      	<AuditTrail name="log4j_audittrail" />
	<!-- 	
		<AuditTrail name="moss_arr_udp" />	
		<AuditTrail name="moss_arr_tls" />	
		
		<AuditTrail name="allscripts_arr_udp" />	
		<AuditTrail name="allscripts_arr_tls" />
		
		<AuditTrail name="forcare_arr_udp" />	
		<AuditTrail name="forcare_arr_tls" />
		
		<AuditTrail name="medecision_arr_udp" />	
		<AuditTrail name="medecision_arr_tls" />

		<AuditTrail name="medicity_arr_udp" />	
		<AuditTrail name="medicity_arr_tls" />

		<AuditTrail name="ibm_arr_udp" />	
		<AuditTrail name="ibm_arr_tls" />

		<AuditTrail name="ith-icoserve_arr_udp" />	
		<AuditTrail name="ith-icoserve_arr_tls" />
			
		<AuditTrail name="karos_arr_udp" />	
		<AuditTrail name="karos_arr_tls" />

		<AuditTrail name="oracle_ehr_arr_udp" />	
		<AuditTrail name="oracle_ehr_arr_tls" />	
		<AuditTrail name="oracle_pix_arr_udp" />	
		<AuditTrail name="oracle_pix_arr_tls" />	
		
		<AuditTrail name="tiani_ehr_arr_udp" />	
		<AuditTrail name="tiani_ehr_arr_tls" />	
		<AuditTrail name="tiani_pacs_arr_udp" />	
		<AuditTrail name="tiani_pacs_arr_tls" />	
		
		<AuditTrail name="vangent_arr_udp" />	
		<AuditTrail name="vangent_arr_tls" />
	 -->
    </Actor>

</Configuration>